iclearn/__init__.py
iclearn/main_cli.py
iclearn/py.typed
iclearn/cli/__init__.py
iclearn/cli/cli.py
iclearn/cli/infer.py
iclearn/cli/preview.py
iclearn/cli/train.py
iclearn/data/__init__.py
iclearn/data/dataloader.py
iclearn/data/dataloader_collection.py
iclearn/data/split.py
iclearn/data/image/__init__.py
iclearn/data/image/image.py
iclearn/data/utils/linear/__init__.py
iclearn/data/utils/linear/config.py
iclearn/data/utils/linear/linear_data.py
iclearn/data/utils/linear/torch/__init__.py
iclearn/data/utils/linear/torch/linear_data.py
iclearn/environment/__init__.py
iclearn/environment/environment.py
iclearn/environment/frameworks.py
iclearn/environment/torch/__init__.py
iclearn/environment/torch/cuda_info.py
iclearn/environment/torch/dist_utils.py
iclearn/environment/torch/environment.py
iclearn/model/__init__.py
iclearn/model/loss_functions.py
iclearn/model/machine_learning_model.py
iclearn/model/metrics.py
iclearn/model/metrics_cache.py
iclearn/model/metrics_loader.py
iclearn/model/model.py
iclearn/model/model_collection.py
iclearn/model/optimizers.py
iclearn/model/stopping_criteria.py
iclearn/model/torch/__init__.py
iclearn/model/torch/loss_functions.py
iclearn/model/torch/metrics.py
iclearn/model/torch/model.py
iclearn/model/torch/model_collection.py
iclearn/model/torch/optimizers.py
iclearn/model/utils/__init__.py
iclearn/model/utils/linear_functions.py
iclearn/output/__init__.py
iclearn/output/logging_output_handler.py
iclearn/output/mlflow_output_handler.py
iclearn/output/output_handler.py
iclearn/output/output_handler_collection.py
iclearn/output/plotting_output_handler.py
iclearn/output/tabular_output_handler.py
iclearn/output/torch/__init__.py
iclearn/output/torch/tensorboard_output_handler.py
iclearn/session/__init__.py
iclearn/session/session.py
iclearn/session/train_config.py
iclearn/session/train_session.py
iclearn/session/torch/__init__.py
iclearn/session/torch/session.py
iclearn/utils/__init__.py
iclearn/utils/profiler.py
iclearn-0.1.6.dist-info/licenses/LICENSE
iclearn-0.1.6.dist-info/METADATA
iclearn-0.1.6.dist-info/WHEEL
iclearn-0.1.6.dist-info/entry_points.txt
iclearn-0.1.6.dist-info/top_level.txt
iclearn-0.1.6.dist-info/RECORD
