Metadata-Version: 2.4
Name: iclearn
Version: 0.1.6
Summary: A collection of utilities for machine learning applications.
Author-email: "James Grogan, Irish Centre for High End Computing" <james.grogan@ichec.ie>
Project-URL: Repository, https://git.ichec.ie/performance/toolshed/iclearn
Project-URL: Homepage, https://git.ichec.ie/performance/toolshed/iclearn
Keywords: Machine Learning,Workflow,HPC
Classifier: Development Status :: 3 - Alpha
Classifier: Programming Language :: Python :: 3
Classifier: License :: OSI Approved :: GNU General Public License v3 or later (GPLv3+)
Classifier: Operating System :: OS Independent
Classifier: Topic :: System :: Distributed Computing
Requires-Python: >=3.10
License-File: LICENSE
Requires-Dist: icsystemutils==0.2.5
Requires-Dist: icplot==0.2.4
Requires-Dist: mlflow
Requires-Dist: tensorboard
Requires-Dist: opencv-python-headless
Provides-Extra: test
Requires-Dist: pytest; extra == "test"
Requires-Dist: pytest-cov; extra == "test"
Requires-Dist: pytest-sugar; extra == "test"
Requires-Dist: black; extra == "test"
Requires-Dist: flake8; extra == "test"
Requires-Dist: pylint; extra == "test"
Requires-Dist: mypy; extra == "test"
Provides-Extra: torch
Requires-Dist: torch; extra == "torch"
Requires-Dist: torchvision; extra == "torch"
Dynamic: license-file
